dict_deep/__init__.py
dict_deep/dict_deep.py
dict_deep-4.1.1.dist-info/LICENSE.txt
dict_deep-4.1.1.dist-info/WHEEL
dict_deep-4.1.1.dist-info/METADATA
dict_deep-4.1.1.dist-info/RECORD
