Metadata-Version: 2.1
Name: dict-deep
Version: 4.1.1
Summary: Very simple deep_set and deep_get functions to access nested dicts (or any object) using 'dotted strings' as key.
Home-page: https://github.com/mbello/dict-deep
License: MIT
Keywords: dict dotted keys,deep dict access,nested dict access,deep_get,deep_set,deep_del
Author: mbello
Author-email: mbello@users.noreply.github.com
Requires-Python: >=3.5,<4.0
Classifier: License :: OSI Approved :: MIT License
Classifier: Programming Language :: Python :: 3
Classifier: Programming Language :: Python :: 3.5
Classifier: Programming Language :: Python :: 3.6
Classifier: Programming Language :: Python :: 3.7
Classifier: Programming Language :: Python :: 3.8
Project-URL: Repository, https://github.com/mbello/dict-deep
